MANIFEST.in
README.md
setup.py
fspotlib/__init__.py
fspotlib/core.py
fspotlib/someconf.json
fspotlib.egg-info/PKG-INFO
fspotlib.egg-info/SOURCES.txt
fspotlib.egg-info/dependency_links.txt
fspotlib.egg-info/entry_points.txt
fspotlib.egg-info/requires.txt
fspotlib.egg-info/top_level.txt