Metadata-Version: 1.0
Name: fspotlib
Version: 0.0.2
Summary: test publishing on pypi
Home-page: http://github.com/fspot/fspotlib
Author: fspot
Author-email: fred@fspot.org
License: WTFPL
Platform: UNKNOWN
